behave4cli/README.txt
behave4cli/__all_steps__.py
behave4cli/__init__.py
behave4cli/__setup.py
behave4cli/__version__.py
behave4cli/command_shell.py
behave4cli/command_shell_proc.py
behave4cli/command_steps.py
behave4cli/command_util.py
behave4cli/failing_steps.py
behave4cli/log/__init__.py
behave4cli/log/steps.py
behave4cli/note_steps.py
behave4cli/passing_steps.py
behave4cli/pathutil.py
behave4cli/setup_command_shell.py
behave4cli/textutil.py
behave4cli-1.1.3.dist-info/LICENSE
behave4cli-1.1.3.dist-info/WHEEL
behave4cli-1.1.3.dist-info/METADATA
behave4cli-1.1.3.dist-info/RECORD
